_k2.cpython-36m-x86_64-linux-gnu.so
libcontext.so
libfsa.so
k2/__init__.py
k2/array.py
k2/fsa.py
k2/symbol_table.py
k2_fsa-0.0.5.data/data/LICENSE
k2_fsa-0.0.5.dist-info/LICENSE
k2_fsa-0.0.5.dist-info/METADATA
k2_fsa-0.0.5.dist-info/WHEEL
k2_fsa-0.0.5.dist-info/top_level.txt
k2_fsa-0.0.5.dist-info/RECORD
