Metadata-Version: 2.1
Name: k2-fsa
Version: 0.0.5
Summary: FSA/FST algorithms, intended to (eventually) be interoperable with PyTorch and similar
Home-page: https://github.com/k2-fsa/k2
Author: Daniel Povey
Author-email: dpovey@gmail.com
License: UNKNOWN
Keywords: k2,FSA,FST
Platform: UNKNOWN
Classifier: Development Status :: 3 - Alpha
Classifier: Programming Language :: Python :: 3
Classifier: Programming Language :: C++
Classifier: Programming Language :: Python :: Implementation :: CPython
Classifier: Topic :: Scientific/Engineering :: Artificial Intelligence
Classifier: Operating System :: OS Independent
Requires-Python: >=3.6
Requires-Dist: torch
Requires-Dist: graphviz
